Metadata-Version: 2.1
Name: pro-curso-dev
Version: 1.0
Summary: Este pacote irá fornecer ferramentas de processamento de vídeo
Author: Eduardo
Author-email: alguemai@gmail.com
Keywords: camera,video,processamento
License-File: license.txt
